omnidict/__init__.py
omnidict/caching.py
omnidict/repositories.py
omnidict-1.0.0a8.dist-info/licenses/LICENSE
omnidict-1.0.0a8.dist-info/METADATA
omnidict-1.0.0a8.dist-info/WHEEL
omnidict-1.0.0a8.dist-info/top_level.txt
omnidict-1.0.0a8.dist-info/RECORD
