Metadata-Version: 2.4
Name: omnidict
Version: 1.0.0a8
Summary: Common interface for many key-value storages
Author-email: "Santiago B. Perez Pita" <santibreo@gmail.com>
License:                     GNU GENERAL PUBLIC LICENSE
Requires-Python: >=3.11
License-File: LICENSE
Requires-Dist: packaging<25,==24.2
Requires-Dist: cryptography<45,>=44.0.1
Provides-Extra: dev
Requires-Dist: black; extra == "dev"
Requires-Dist: ruff; extra == "dev"
Requires-Dist: fakeredis; extra == "dev"
Requires-Dist: coverage; extra == "dev"
Requires-Dist: pre-commit; extra == "dev"
Requires-Dist: pytest; extra == "dev"
Requires-Dist: mypy; extra == "dev"
Requires-Dist: ipython; extra == "dev"
Requires-Dist: ipdb; extra == "dev"
Dynamic: license-file
